amlutils/__init__.py
amlutils/csv_utils.py
amlutils/json_utils.py
amlutils/annotations/__init__.py
amlutils/annotations/annotation_image_mapping.py
amlutils/collections/__init__.py
amlutils/collections/lists.py
amlutils/files_and_folders/__init__.py
amlutils/files_and_folders/file_utils.py
amlutils/files_and_folders/folder_utils.py
amlutils/files_and_folders/utils.py
amlutils/image/__init__.py
amlutils/image/augment.py
amlutils/sorting/__init__.py
amlutils/sorting/natural_sort.py
amlutils/video/__init__.py
amlutils/video/utils.py
amlutils/web/__init__.py
amlutils/web/download.py
amlutils/web/requests.py
amlutils/xmls/__init__.py
amlutils/xmls/create.py
amlutils/xmls/parse.py
tests/__init__.py
tests/test_csv_utils.py
tests/test_json_utils.py
tests/annotations/__init__.py
tests/annotations/test_annotation_image_mapping.py
tests/collections/__init__.py
tests/collections/test_lists.py
tests/files_and_folders/__init__.py
tests/files_and_folders/test_file_and_folder_utils.py
tests/sorting/__init__.py
tests/sorting/test_natural_sort.py
tests/video/__init__.py
tests/video/test_video_utils.py
tests/xmls/__init__.py
tests/xmls/test_xml_parse.py
amlutils-2.0.0.dist-info/LICENSE
amlutils-2.0.0.dist-info/METADATA
amlutils-2.0.0.dist-info/WHEEL
amlutils-2.0.0.dist-info/top_level.txt
amlutils-2.0.0.dist-info/RECORD
