Metadata-Version: 2.1
Name: amlutils
Version: 2.0.0
Summary: A collection of useful methods and utilities for Machine Learning Projects
Home-page: https://github.com/parvoberoi/amlutils
Author: Parv Oberoi
Author-email: amlutils@gmail.com
License: Apache Software License
Platform: UNKNOWN
Classifier: Development Status :: 3 - Alpha
Classifier: Intended Audience :: Developers
Classifier: Programming Language :: Python :: 3
Classifier: License :: OSI Approved :: Apache Software License
Classifier: Operating System :: OS Independent
Classifier: Topic :: Scientific/Engineering :: Artificial Intelligence
Requires-Python: >=3.6
Requires-Dist: Pillow (>=8.0.1)
Requires-Dist: numpy (>=1.18.3)
Requires-Dist: opencv-python (>=4.2.0.34)
Requires-Dist: requests (>=2.23.0)
